AUTHORS
LICENCE
MANIFEST.in
README.md
setup.py
django_tinystore.egg-info/PKG-INFO
django_tinystore.egg-info/SOURCES.txt
django_tinystore.egg-info/dependency_links.txt
django_tinystore.egg-info/top_level.txt
tinystore/__init__.py
tinystore/admin.py
tinystore/apps.py
tinystore/models.py
tinystore/tests.py
tinystore/migrations/0001_initial.py
tinystore/migrations/__init__.py
www/__init__.py
www/asgi.py
www/settings.py
www/urls.py
www/wsgi.py